{
  "type": "create:sequenced_assembly",
  "ingredient": {
    "item": "create_cobblemon:ancient_wing_ball_lid"
  },
  "transitionalItem": {
    "item": "create_cobblemon:incomplete_ancient_wing_ball"
  },
  "sequence": [
    {
      "type": "create:deploying",
      "ingredients": [
        {
          "item": "create_cobblemon:incomplete_ancient_wing_ball"
        },
        [
          {
            "item": "create_cobblemon:iron_ball_base"
          }
        ]
      ],
      "results": [
        {
          "item": "create_cobblemon:incomplete_ancient_wing_ball"
        }
      ]
    },
    {
      "type": "create:deploying",
      "ingredients": [
        {
          "item": "create_cobblemon:incomplete_ancient_wing_ball"
        },
        [
          {
            "item": "minecraft:iron_nugget"
          }
        ]
      ],
      "results": [
        {
          "item": "create_cobblemon:incomplete_ancient_wing_ball"
        }
      ]
    }
  ],
  "results": [
    {
      "item": "cobblemon:ancient_wing_ball"
    }
  ],
  "loops": 1
}